deputydev_cli-1.0.4.data/purelib/app/__init__.py
deputydev_cli-1.0.4.data/purelib/app/listeners.py
deputydev_cli-1.0.4.data/purelib/app/service.py
deputydev_cli-1.0.4.data/purelib/app/common/__init__.py
deputydev_cli-1.0.4.data/purelib/app/common/constants/__init__.py
deputydev_cli-1.0.4.data/purelib/app/common/constants/auth.py
deputydev_cli-1.0.4.data/purelib/app/common/constants/constants.py
deputydev_cli-1.0.4.data/purelib/app/common/constants/error_codes.py
deputydev_cli-1.0.4.data/purelib/app/common/constants/error_messages.py
deputydev_cli-1.0.4.data/purelib/app/common/constants/feedbacks.py
deputydev_cli-1.0.4.data/purelib/app/common/constants/success_messages.py
deputydev_cli-1.0.4.data/purelib/app/common/exception/__init__.py
deputydev_cli-1.0.4.data/purelib/app/common/exception/exception.py
deputydev_cli-1.0.4.data/purelib/app/common/models/dao/weaviate/base.py
deputydev_cli-1.0.4.data/purelib/app/common/models/dao/weaviate/chunk_files.py
deputydev_cli-1.0.4.data/purelib/app/common/models/dao/weaviate/chunks.py
deputydev_cli-1.0.4.data/purelib/app/common/models/dao/weaviate/constants/collection_names.py
deputydev_cli-1.0.4.data/purelib/app/common/models/dto/chunk_dto.py
deputydev_cli-1.0.4.data/purelib/app/common/models/dto/chunk_file_dto.py
deputydev_cli-1.0.4.data/purelib/app/common/request_clients/http/base_http_client.py
deputydev_cli-1.0.4.data/purelib/app/common/request_clients/http/base_http_session_manager.py
deputydev_cli-1.0.4.data/purelib/app/common/request_clients/http/adapters/http_response_adapter.py
deputydev_cli-1.0.4.data/purelib/app/common/services/__init__.py
deputydev_cli-1.0.4.data/purelib/app/common/services/authentication/jwt.py
deputydev_cli-1.0.4.data/purelib/app/common/services/chunking/__init__.py
deputydev_cli-1.0.4.data/purelib/app/common/services/chunking/chunk.py
deputydev_cli-1.0.4.data/purelib/app/common/services/chunking/chunk_info.py
deputydev_cli-1.0.4.data/purelib/app/common/services/chunking/chunking_manager.py
deputydev_cli-1.0.4.dist-info/METADATA
deputydev_cli-1.0.4.dist-info/WHEEL
deputydev_cli-1.0.4.dist-info/entry_points.txt
deputydev_cli-1.0.4.dist-info/top_level.txt
deputydev_cli-1.0.4.dist-info/RECORD
