Metadata-Version: 2.2
Name: deputydev_cli
Version: 1.0.4
Summary: DeputyDev CLI is an AI-powered coding companion that streamlines software development with four core features: Code Generation to translate natural language into code, Documentation Generation for custom docstrings, Task Planning to structure development steps, and Test Generation for automated unit tests. This tool is designed to reduce development overhead and enhance coding productivity.
Author-email: DeputyDev <deputydev@1mg.com>
Project-URL: Homepage, https://deputydev.ai
Requires-Python: <3.12,>=3.9
Requires-Dist: tortoise-orm==0.21.3
Requires-Dist: langchain==0.0.344
Requires-Dist: psycopg2-binary==2.9.9
Requires-Dist: tiktoken==0.7.0
Requires-Dist: pgvector==0.2.4
Requires-Dist: pandas==2.1.3
Requires-Dist: numpy==1.26.2
Requires-Dist: openai==1.5.0
Requires-Dist: pypdf==4.0.1
Requires-Dist: pillow==10.2.0
Requires-Dist: google-generativeai==0.3.2
Requires-Dist: tree-sitter-languages==1.10.2
Requires-Dist: tree-sitter==0.21.0
Requires-Dist: tree-sitter-javascript==0.21.0
Requires-Dist: pyjwt==2.9.0
Requires-Dist: prompt-toolkit==3.0.48
Requires-Dist: xxhash==3.5.0
Requires-Dist: weaviate-client==4.9.6
Requires-Dist: sanic==22.12.0
Requires-Dist: gitpython==3.1.27
Requires-Dist: giturlparse==0.12.0
